{
    "products": [
        {
            "id": 1,
            "name": "Tênis Futurista",
            "category": "Tênis",
            "price": 150.00,
            "discount_percentage": 20,
            "promotional_price": 120.00,
            "image": "https://s3-sa-east-1.amazonaws.com/prod-superon-public-media/prova-frontend/shoes/shoes-1.jpg",
            "description": "Tênis futurista com design inovador e confortável. Ideal para quem busca estilo e conforto."
        },
        {
            "id": 2,
            "name": "Chuteira",
            "category": "Tênis",
            "price": 250.00,
            "image": "https://s3-sa-east-1.amazonaws.com/prod-superon-public-media/prova-frontend/shoes/shoes-2.jpg",
            "description": "Chuteira para futebol de campo, com travas de borracha e material resistente. Ideal para quem busca desempenho e conforto."
        },
        {
            "id": 3,
            "name": "Tênis 3",
            "category": "Tênis",
            "price": 350.00,
            "image": "https://s3-sa-east-1.amazonaws.com/prod-superon-public-media/prova-frontend/shoes/shoes-3.jpg",
            "description": "Tênis 3 com design inovador e confortável. Ideal para quem busca estilo e conforto."
        },
        {
            "id": 4,
            "name": "Scarpin Vermelho",
            "category": "Tênis",
            "price": 450.00,
            "image": "https://s3-sa-east-1.amazonaws.com/prod-superon-public-media/prova-frontend/shoes/shoes-4.jpg",
            "description": "Scarpin vermelho com salto alto e design elegante. Ideal para festas e eventos."
        },
        {
            "id": 5,
            "name": "Sapatênis",
            "category": "Tênis",
            "price": 550.00,
            "image": "https://s3-sa-east-1.amazonaws.com/prod-superon-public-media/prova-frontend/shoes/shoes-5.jpg",
            "description": "Sapatênis com design inovador e confortável. Ideal para quem busca estilo e conforto."
        },
        {
            "id": 6,
            "name": "Camiseta Rosa",
            "category": "Camisetas",
            "price": 50.00,
            "discount_percentage": 10,
            "promotional_price": 45.00,
            "image": "https://s3-sa-east-1.amazonaws.com/prod-superon-public-media/prova-frontend/tshirts/tshirt-1.jpg",
            "description": "Camiseta rosa com design inovador e confortável. Ideal para quem busca estilo e conforto."
        },
        {
            "id": 7,
            "name": "Camiseta Branca",
            "category": "Camisetas",
            "price": 60.00,
            "image": "https://s3-sa-east-1.amazonaws.com/prod-superon-public-media/prova-frontend/tshirts/tshirt-2.jpg",
            "description": "Camiseta branca com design inovador e confortável. Ideal para quem busca estilo e conforto."
        },
        {
            "id": 8,
            "name": "Camiseta Pac-Man",
            "category": "Camisetas",
            "price": 70.00,
            "image": "https://s3-sa-east-1.amazonaws.com/prod-superon-public-media/prova-frontend/tshirts/tshirt-3.jpg",
            "description": "Camiseta com estampa do Pac-Man. Ideal para quem busca estilo e conforto."
        },
        {
            "id": 9,
            "name": "Camiseta No Plans",
            "category": "Camisetas",
            "price": 80.00,
            "image": "https://s3-sa-east-1.amazonaws.com/prod-superon-public-media/prova-frontend/tshirts/tshirt-4.jpg",
            "description": "Camiseta com estampa No Plans. Ideal para quem busca estilo e conforto."
        },
        {
            "id": 10,
            "name": "Camiseta Básica Marrom",
            "category": "Camisetas",
            "price": 90.00,
            "image": "https://s3-sa-east-1.amazonaws.com/prod-superon-public-media/prova-frontend/tshirts/tshirt-5.jpg",
            "description": "Camiseta básica marrom com design inovador e confortável. Ideal para quem busca estilo e conforto."
        },
        {
            "id": 11,
            "name": "Calça Cinza",
            "category": "Calças",
            "price": 100.00,
            "image": "https://s3-sa-east-1.amazonaws.com/prod-superon-public-media/prova-frontend/pants/pant-1.jpg",
            "description": "Calça cinza com design inovador e confortável. Ideal para quem busca estilo e conforto."
        },
        {
            "id": 12,
            "name": "Calça Verde",
            "category": "Calças",
            "price": 110.00,
            "discount_percentage": 10,
            "promotional_price": 99.00,
            "image": "https://s3-sa-east-1.amazonaws.com/prod-superon-public-media/prova-frontend/pants/pant-2.jpg",
            "description": "Calça verde com design inovador e confortável. Ideal para quem busca estilo e conforto."
        },
        {
            "id": 13,
            "name": "Kit Calça Jeans",
            "category": "Calças",
            "price": 120.00,
            "image": "https://s3-sa-east-1.amazonaws.com/prod-superon-public-media/prova-frontend/pants/pant-3.jpg",
            "description": "Kit com 3 calças jeans de cores diferentes. Ideal para quem busca estilo e conforto."
        },
        {
            "id": 14,
            "name": "Calça Jeans Feminina",
            "category": "Calças",
            "price": 130.00,
            "image": "https://s3-sa-east-1.amazonaws.com/prod-superon-public-media/prova-frontend/pants/pant-4.jpg",
            "description": "Calça jeans feminina com design inovador e confortável. Ideal para quem busca estilo e conforto."
        },
        {
            "id": 15,
            "name": "Calça Militar",
            "category": "Calças",
            "price": 140.00,
            "image": "https://s3-sa-east-1.amazonaws.com/prod-superon-public-media/prova-frontend/pants/pant-5.jpg",
            "description": "Calça militar com design inovador e confortável. Ideal para quem busca estilo e conforto."
        }        
    ]
}